useapp/__init__.py
useapp/admin.py
useapp/apps.py
useapp/models.py
useapp/signals.py
useapp/tests.py
useapp/urls.py
useapp/views.py
useapp/migrations/__init__.py
useapp/template/notifications/list.html
useapp-0.2.0.dist-info/METADATA
useapp-0.2.0.dist-info/WHEEL
useapp-0.2.0.dist-info/top_level.txt
useapp-0.2.0.dist-info/RECORD
